fast_vindex/__init__.py
fast_vindex/api.py
fast_vindex/array/__init__.py
fast_vindex/array/core.py
fast_vindex/testing/__init__.py
fast_vindex/testing/core.py
fast_vindex/testing/plot.py
fast_vindex-0.0.3.dist-info/METADATA
fast_vindex-0.0.3.dist-info/WHEEL
fast_vindex-0.0.3.dist-info/licenses/LICENSE
fast_vindex-0.0.3.dist-info/RECORD
