Metadata-Version: 2.4
Name: fast-vindex
Version: 0.0.3
Summary: A faster version of Dask's vindex for advanced indexing with arrays.
Project-URL: Homepage, https://gitlab.ifremer.fr/odatis-public/fast_vindex
Project-URL: Documentation, https://odatis-public.gitlab-pages.ifremer.fr/fast_vindex
Author-email: Gwenaël CAËR <gwenael.caer@data-terra.org>
License:                    GNU LESSER GENERAL PUBLIC LICENSE
License-File: LICENSE
Requires-Python: >=3.11
Requires-Dist: dask>=2025.1.0
Requires-Dist: matplotlib
Requires-Dist: numpy>=1.26
Requires-Dist: pandas>=2.2
Requires-Dist: xarray
Provides-Extra: test
Requires-Dist: pytest-cov>=4.0; extra == 'test'
Requires-Dist: pytest>=7.4; extra == 'test'
